ayuabtu/__init__.py
ayuabtu/quantities/__init__.py
ayuabtu/quantities/electricCurrent.py
ayuabtu/quantities/length.py
ayuabtu/quantities/mass.py
ayuabtu/quantities/time.py
ayuabtu/units/__init__.py
ayuabtu/units/electricCurrentUnit.py
ayuabtu/units/lengthUnit.py
ayuabtu/units/massUnit.py
ayuabtu/units/timeUnit.py
tests/__init__.py
tests/test_length.py
ayuabtu-0.0.3.dist-info/LICENSE
ayuabtu-0.0.3.dist-info/METADATA
ayuabtu-0.0.3.dist-info/WHEEL
ayuabtu-0.0.3.dist-info/top_level.txt
ayuabtu-0.0.3.dist-info/RECORD
