Metadata-Version: 2.1
Name: ayuabtu
Version: 0.0.3
Summary: A package for units.
Home-page: https://github.com/MCHalbi/AllYourUnitAreBelongToUs
Author: Lukas Halbritter
Author-email: halbi93@gmx.de
License: UNKNOWN
Platform: UNKNOWN
Requires-Python: >=3.5
